[
  {
    "query": "为什么有些人的预判能力这么强",
    "display_query": "为什么有些人的预判能力这么强"
  },
  {
    "query": "为什么说男人至死都是少年",
    "display_query": "为什么说男人至死都是少年"
  },
  { "query": "你因为什么事情报过警", "display_query": "你因为什么事情报过警" },
  { "query": "宗馥莉", "display_query": "宗馥莉" },
  { "query": "发现孩子很普通怎么办", "display_query": "发现孩子很普通怎么办" },
  {
    "query": "常年独居的人靠什么抵抗孤独",
    "display_query": "常年独居的人靠什么抵抗孤独"
  },
  { "query": "诺贝尔物理学奖揭晓", "display_query": "诺贝尔物理学奖揭晓" },
  {
    "query": "打工人有哪些「至爽时刻」",
    "display_query": "打工人有哪些「至爽时刻」"
  },
  { "query": "一部电影会失传吗", "display_query": "一部电影会失传吗" },
  {
    "query": "如何看待美国识字率只有 79％",
    "display_query": "如何看待美国识字率只有 79％"
  },
  { "query": "2025 诺贝尔经济学奖", "display_query": "2025 诺贝尔经济学奖" },
  { "query": "宗馥莉已辞职", "display_query": "宗馥莉已辞职" },
  {
    "query": "成都一车辆起火多人救援打不开门",
    "display_query": "成都一车辆起火多人救援打不开门"
  },
  {
    "query": "中方回应美方威胁加征100%关税",
    "display_query": "中方回应美方威胁加征100%关税"
  },
  {
    "query": "工作中你捅过多大的娄子结果怎么样",
    "display_query": "工作中你捅过多大的娄子结果怎么样"
  },
  { "query": "美股跳水", "display_query": "美股跳水" },
  {
    "query": "万科董事长辛杰被曝失联",
    "display_query": "万科董事长辛杰被曝失联"
  },
  {
    "query": "风林火山为何无法让港片复兴",
    "display_query": "风林火山为何无法让港片复兴"
  },
  {
    "query": "浙江一居民楼出现空心菜瀑布",
    "display_query": "浙江一居民楼出现空心菜瀑布"
  },
  {
    "query": "宗馥莉将独立经营娃小宗",
    "display_query": "宗馥莉将独立经营娃小宗"
  },
  {
    "query": "杜鲁门号与货船相撞后用海报遮挡",
    "display_query": "杜鲁门号与货船相撞后用海报遮挡"
  },
  {
    "query": "听过领导最没水平的一句话是什么",
    "display_query": "听过领导最没水平的一句话是什么"
  },
  {
    "query": "闻泰科技147亿半导体资产被荷兰冻结",
    "display_query": "闻泰科技147亿半导体资产被荷兰冻结"
  },
  {
    "query": "你去过最离谱的景区是什么",
    "display_query": "你去过最离谱的景区是什么"
  },
  {
    "query": "为什么当今社会单亲妈妈越来越多了",
    "display_query": "为什么当今社会单亲妈妈越来越多了"
  },
  { "query": "哪些演员演什么像什么", "display_query": "哪些演员演什么像什么" },
  {
    "query": "过去24小时加密货币爆仓超190亿美元",
    "display_query": "过去24小时加密货币爆仓超190亿美元"
  },
  {
    "query": "蜜雪冰城多地门店柠檬水缺货",
    "display_query": "蜜雪冰城多地门店柠檬水缺货"
  },
  {
    "query": "现实中出轨的人真的很多吗",
    "display_query": "现实中出轨的人真的很多吗"
  },
  {
    "query": "恒大许家印离岸信托被击穿",
    "display_query": "恒大许家印离岸信托被击穿"
  },
  {
    "query": "你有什么一辈子不能说的秘密",
    "display_query": "你有什么一辈子不能说的秘密"
  },
  {
    "query": "为何现在我国大学都希望变成综合性大学",
    "display_query": "为何现在我国大学都希望变成综合性大学"
  },
  {
    "query": "动物园羊驼被投喂吃撑倒地",
    "display_query": "动物园羊驼被投喂吃撑倒地"
  },
  {
    "query": "俄罗斯一废弃气象站布满北极熊",
    "display_query": "俄罗斯一废弃气象站布满北极熊"
  },
  {
    "query": "如何解读男子拒服兵役受多项处罚",
    "display_query": "如何解读男子拒服兵役受多项处罚"
  },
  {
    "query": "为何很多人认为一辆车开五六年就要换车",
    "display_query": "为何很多人认为一辆车开五六年就要换车"
  },
  {
    "query": "中国海警回应菲船侵闯铁线礁",
    "display_query": "中国海警回应菲船侵闯铁线礁"
  },
  {
    "query": "张继科说凭啥不知情时换教练",
    "display_query": "张继科说凭啥不知情时换教练"
  },
  {
    "query": "游客在景区捡板栗被民宿诬陷偷盗索赔",
    "display_query": "游客在景区捡板栗被民宿诬陷偷盗索赔"
  },
  {
    "query": "为什么几乎所有电视的投屏软件都被乐播垄断",
    "display_query": "为什么几乎所有电视的投屏软件都被乐播垄断"
  }
]
