[
  {
    "query": "东风5C打击范围覆盖全球",
    "display_query": "东风5C打击范围覆盖全球"
  },
  {
    "query": "上海夫妻遭遇现实版「寄生虫」",
    "display_query": "上海夫妻遭遇现实版「寄生虫」"
  },
  { "query": "月全食", "display_query": "月全食" },
  {
    "query": "桃李面包称领导正接受现实毒打",
    "display_query": "桃李面包称领导正接受现实毒打"
  },
  {
    "query": "武汉大学回应椅子标签争议",
    "display_query": "武汉大学回应椅子标签争议"
  },
  { "query": "歼 20S 有哪些提升", "display_query": "歼 20S 有哪些提升" },
  {
    "query": "中国证监会原主席易会满被查",
    "display_query": "中国证监会原主席易会满被查"
  },
  {
    "query": "央行开展 1 万亿买断式逆回购",
    "display_query": "央行开展 1 万亿买断式逆回购"
  },
  { "query": "兵马俑一号坑惊现大洞", "display_query": "兵马俑一号坑惊现大洞" },
  {
    "query": "杨靖宇支队战旗光荣受阅",
    "display_query": "杨靖宇支队战旗光荣受阅"
  },
  {
    "query": "《流浪地球》系列电影中哪些装备过时了",
    "display_query": "《流浪地球》系列电影中哪些装备过时了"
  },
  {
    "query": "男子将眼镜王蛇挂脖玩被咬身亡",
    "display_query": "男子将眼镜王蛇挂脖玩被咬身亡"
  },
  { "query": "儿童火车票有新规定了", "display_query": "儿童火车票有新规定了" },
  { "query": "东风-5C 还有哪些亮点", "display_query": "东风-5C 还有哪些亮点" },
  { "query": "歼击机梯队各有何特点", "display_query": "歼击机梯队各有何特点" },
  {
    "query": "北京杜莎夫人蜡像馆将永久关停",
    "display_query": "北京杜莎夫人蜡像馆将永久关停"
  },
  {
    "query": "阅兵装备方队是如何做到「米秒不差」的",
    "display_query": "阅兵装备方队是如何做到「米秒不差」的"
  },
  { "query": "中元节", "display_query": "中元节" },
  {
    "query": "为什么能接受孩子平庸却无法忍受作业拖拉",
    "display_query": "为什么能接受孩子平庸却无法忍受作业拖拉"
  },
  {
    "query": "九三阅兵中有哪些新式武器亮相",
    "display_query": "九三阅兵中有哪些新式武器亮相"
  },
  {
    "query": "为什么战旗方队给杨靖宇支队这么多镜头",
    "display_query": "为什么战旗方队给杨靖宇支队这么多镜头"
  },
  { "query": "steam 崩了", "display_query": "steam 崩了" },
  {
    "query": "为什么今年在 9 月 3 号大阅兵",
    "display_query": "为什么今年在 9 月 3 号大阅兵"
  },
  { "query": "丝之歌", "display_query": "丝之歌" },
  {
    "query": "携程全员居家办公对员工来说是好事吗",
    "display_query": "携程全员居家办公对员工来说是好事吗"
  },
  {
    "query": "陆军新一代装甲装备有哪些亮点",
    "display_query": "陆军新一代装甲装备有哪些亮点"
  },
  {
    "query": "九三阅兵时美国五角大楼附近披萨订单激增",
    "display_query": "九三阅兵时美国五角大楼附近披萨订单激增"
  },
  {
    "query": "刘老庒连旗帜上的庒字多了一点",
    "display_query": "刘老庒连旗帜上的庒字多了一点"
  },
  {
    "query": "26国将向乌克兰部署军队",
    "display_query": "26国将向乌克兰部署军队"
  },
  { "query": "DF61 导弹威力有多大", "display_query": "DF61 导弹威力有多大" },
  { "query": "九三阅兵现场关注", "display_query": "九三阅兵现场关注" },
  {
    "query": "核导弹第一方队代表了怎样的作战能力",
    "display_query": "核导弹第一方队代表了怎样的作战能力"
  },
  { "query": "麒麟9020", "display_query": "麒麟9020" },
  {
    "query": "百度地图被曝在打车流程中强插广告",
    "display_query": "百度地图被曝在打车流程中强插广告"
  }
]
