[
  { "query": "勇士vs太阳", "display_query": "勇士vs太阳" },
  { "query": "火箭vs湖人", "display_query": "火箭vs湖人" },
  { "query": "掘金大胜森林狼", "display_query": "掘金大胜森林狼" },
  { "query": "为什么山姆这么受欢迎", "display_query": "为什么山姆这么受欢迎" },
  {
    "query": "怎样才能叫做真正会科研的人",
    "display_query": "怎样才能叫做真正会科研的人"
  },
  {
    "query": "美国情报系统现在属于什么水平",
    "display_query": "美国情报系统现在属于什么水平"
  },
  {
    "query": "内心强大的人有什么特点",
    "display_query": "内心强大的人有什么特点"
  },
  {
    "query": "为什么有的人特别容易紧张",
    "display_query": "为什么有的人特别容易紧张"
  },
  { "query": "你曾经错过大牛股吗", "display_query": "你曾经错过大牛股吗" },
  { "query": "什么生活常识必须知道", "display_query": "什么生活常识必须知道" },
  {
    "query": "爱奇艺 CEO 龚宇说科技不是为了取代人",
    "display_query": "爱奇艺 CEO 龚宇说科技不是为了取代人"
  },
  {
    "query": "上海商学院校长吴忠被实名举报学术不端",
    "display_query": "上海商学院校长吴忠被实名举报学术不端"
  },
  {
    "query": "肢体再生可能由环境而非基因决定",
    "display_query": "肢体再生可能由环境而非基因决定"
  },
  { "query": "日本发生7.5级地震", "display_query": "日本发生7.5级地震" },
  { "query": "速览中东危局40小时", "display_query": "速览中东危局40小时" },
  { "query": "何润东翻红", "display_query": "何润东翻红" },
  {
    "query": "蜜蜂为什么要把身上的花粉刮下来",
    "display_query": "蜜蜂为什么要把身上的花粉刮下来"
  },
  { "query": "2026 苏超", "display_query": "2026 苏超" },
  {
    "query": "为什么现在流行反向追剧",
    "display_query": "为什么现在流行反向追剧"
  },
  {
    "query": "拼多多被罚 15.2 亿且暴力阻碍监管",
    "display_query": "拼多多被罚 15.2 亿且暴力阻碍监管"
  },
  {
    "query": "稿费80万的金番作者使用AI写作",
    "display_query": "稿费80万的金番作者使用AI写作"
  },
  {
    "query": "国产光纤部分产品价格暴涨 650%",
    "display_query": "国产光纤部分产品价格暴涨 650%"
  },
  { "query": "苏超宿迁2-0南京", "display_query": "苏超宿迁2-0南京" },
  { "query": "徐州3-0泰州", "display_query": "徐州3-0泰州" },
  {
    "query": "2026 人形机器人半程马拉松赛",
    "display_query": "2026 人形机器人半程马拉松赛"
  },
  { "query": "建议低精力人群查维D", "display_query": "建议低精力人群查维D" },
  {
    "query": "微波炉加热塑料微塑料飙升 125 倍",
    "display_query": "微波炉加热塑料微塑料飙升 125 倍"
  },
  {
    "query": "劳务中介：微信余额不满三百不给面试",
    "display_query": "劳务中介：微信余额不满三百不给面试"
  },
  {
    "query": "为什么云南泼水节变味了",
    "display_query": "为什么云南泼水节变味了"
  },
  {
    "query": "东部战区舰艇编队过航横当水道",
    "display_query": "东部战区舰艇编队过航横当水道"
  },
  { "query": "哈兰德破门", "display_query": "哈兰德破门" },
  { "query": "今日谷雨", "display_query": "今日谷雨" },
  { "query": "山东泰山vs上海海港", "display_query": "山东泰山vs上海海港" },
  { "query": "BLG战胜AL", "display_query": "BLG战胜AL" },
  { "query": "北京晚霞", "display_query": "北京晚霞" },
  {
    "query": "人到中年你突然领悟了什么",
    "display_query": "人到中年你突然领悟了什么"
  },
  {
    "query": "女子频繁表白后被确诊「桃花癫」",
    "display_query": "女子频繁表白后被确诊「桃花癫」"
  },
  {
    "query": "「16 万年一遇」的彗星来了",
    "display_query": "「16 万年一遇」的彗星来了"
  },
  { "query": "库克不再担任苹果 CEO", "display_query": "库克不再担任苹果 CEO" },
  {
    "query": "德国人为什么看重博士学位",
    "display_query": "德国人为什么看重博士学位"
  },
  { "query": "伊朗最新局势", "display_query": "伊朗最新局势" },
  {
    "query": "日本正式允许出口杀伤性武器",
    "display_query": "日本正式允许出口杀伤性武器"
  },
  {
    "query": "女子产后被男友起诉退彩礼分娩费",
    "display_query": "女子产后被男友起诉退彩礼分娩费"
  },
  {
    "query": "19岁女孩挪用1700万当榜一大姐",
    "display_query": "19岁女孩挪用1700万当榜一大姐"
  },
  {
    "query": "如何评价《寻龙诀·觅踪》直接网播",
    "display_query": "如何评价《寻龙诀·觅踪》直接网播"
  },
  {
    "query": "网传酒店打回访电话致住客离婚",
    "display_query": "网传酒店打回访电话致住客离婚"
  },
  {
    "query": "虐死男友3岁儿子凶手被判死缓",
    "display_query": "虐死男友3岁儿子凶手被判死缓"
  },
  {
    "query": "将新能源绿色车牌褪色为白色有何影响",
    "display_query": "将新能源绿色车牌褪色为白色有何影响"
  },
  { "query": "身体素质差怎么改善", "display_query": "身体素质差怎么改善" },
  { "query": "法庭上有什么趣事", "display_query": "法庭上有什么趣事" },
  {
    "query": "为什么现在很多小孩得抑郁",
    "display_query": "为什么现在很多小孩得抑郁"
  },
  {
    "query": "不想让孩子去幼儿园怎么说服老公",
    "display_query": "不想让孩子去幼儿园怎么说服老公"
  },
  { "query": "日本发生7.7级地震", "display_query": "日本发生7.7级地震" },
  {
    "query": "北方什么蔬菜种一颗全家不挨饿",
    "display_query": "北方什么蔬菜种一颗全家不挨饿"
  },
  {
    "query": "柯镇恶为什么被称为大侠",
    "display_query": "柯镇恶为什么被称为大侠"
  },
  { "query": "如何评价柳宗元", "display_query": "如何评价柳宗元" },
  {
    "query": "爱奇艺再发文回应 AI 艺人库事件",
    "display_query": "爱奇艺再发文回应 AI 艺人库事件"
  },
  { "query": "伊朗局势", "display_query": "伊朗局势" },
  {
    "query": "为什么植物在外界生命很顽强",
    "display_query": "为什么植物在外界生命很顽强"
  },
  {
    "query": "你在谷歌地球有什么独特发现",
    "display_query": "你在谷歌地球有什么独特发现"
  },
  {
    "query": "沈梦辰连续4年做热玛吉脸越打越薄",
    "display_query": "沈梦辰连续4年做热玛吉脸越打越薄"
  },
  { "query": "国产光纤全球爆单", "display_query": "国产光纤全球爆单" },
  {
    "query": "人形机器人实际落地价值在哪儿",
    "display_query": "人形机器人实际落地价值在哪儿"
  },
  {
    "query": "李雨桐泄露薛之谦信息被行拘",
    "display_query": "李雨桐泄露薛之谦信息被行拘"
  },
  {
    "query": "万达电影更名为儒意电影",
    "display_query": "万达电影更名为儒意电影"
  },
  { "query": "云南泼水节变味了", "display_query": "云南泼水节变味了" },
  {
    "query": "微信余额不满三百不给面试",
    "display_query": "微信余额不满三百不给面试"
  },
  {
    "query": "绿茶速成班涉及哪些法律问题",
    "display_query": "绿茶速成班涉及哪些法律问题"
  },
  { "query": "中将军衔很厉害吗", "display_query": "中将军衔很厉害吗" },
  { "query": "养什么花是四季都开的", "display_query": "养什么花是四季都开的" },
  { "query": "你知道哪些明显的谣言", "display_query": "你知道哪些明显的谣言" },
  {
    "query": "内存涨价会倒逼软件优化吗",
    "display_query": "内存涨价会倒逼软件优化吗"
  },
  { "query": "工业克苏鲁有多可怕", "display_query": "工业克苏鲁有多可怕" },
  {
    "query": "东部战区舰艇过航横当水道",
    "display_query": "东部战区舰艇过航横当水道"
  }
]
