[
  {
    "query": "将以演员按姓氏笔画排番位",
    "display_query": "将以演员按姓氏笔画排番位"
  },
  { "query": "速览中东危局40小时", "display_query": "速览中东危局40小时" },
  {
    "query": "我国正研究解决地外星球长期生存问题",
    "display_query": "我国正研究解决地外星球长期生存问题"
  },
  {
    "query": "央视「3·15」晚会主题发布",
    "display_query": "央视「3·15」晚会主题发布"
  },
  { "query": "AWE 家的参考系", "display_query": "AWE 家的参考系" },
  { "query": "AWE 是啥？", "display_query": "AWE 是啥？" },
  { "query": "AWE 逛展看什么？", "display_query": "AWE 逛展看什么？" },
  {
    "query": "逛 AWE，问什么显得我很懂",
    "display_query": "逛 AWE，问什么显得我很懂"
  },
  {
    "query": "AWE，智能生活的 next level？",
    "display_query": "AWE，智能生活的 next level？"
  },
  {
    "query": "杨旭文空降 AWE 知乎展台",
    "display_query": "杨旭文空降 AWE 知乎展台"
  }
]
